app_executor.py
auth_manager.py
cleanup.py
cloud_storage_adapter.py
cogzia_api_key_client.py
config.py
default_config.py
demo_workflow.py
main.py
mcp.py
post_install.py
semantic_matcher.py
services.py
ui.py
ui_components.py
universal_discovery.py
update_manager.py
utils.py
validation.py
version.py
tests/__init__.py
tests/manual_universal_test.py
tests/test_app_executor.py
tests/test_config.py
tests/test_real_user_flow.py
tests/test_service_naming_integration.py
tests/test_universal_discovery_unit.py
tests/test_universal_quick.py
tests/test_universal_server_integration.py
tests/test_user_app_library.py
tests/test_utils.py
tests/integration/__init__.py
tests/integration/test_api_key_client.py
tests/integration/test_api_key_integration.py
tests/integration/test_conversation_flow.py
tests/integration/test_conversation_memory.py
tests/integration/test_deployed_universal.py
tests/integration/test_direct_conversation.py
tests/integration/test_interactive_session.py
tests/integration/test_last_command.py
tests/integration/test_last_command_final.py
tests/integration/test_last_command_interactive.py
tests/integration/test_last_command_simple.py
tests/integration/test_multi_turn_conversation.py
tests/integration/test_pip_install.py
tests/integration/test_real_multi_turn.py
tests/integration/test_secret.py
tests/integration/test_secret_debug.py
tests/integration/test_streaming_simulation.py
tests/integration/test_tool_streaming.py
tests/integration/test_update_integration.py
tests/integration/test_working_integration.py
tests/ui/__init__.py
tests/ui/test_quick_access.py
tests/ui/test_ui_components.py
tests/unit/__init__.py
tests/unit/test_discovery_timing.py
tests/unit/test_gcp_config.py
tests/unit/test_installer.py
tests/unit/test_k8s_services.py
tests/unit/test_simple.py
tests/unit/test_update_manager.py
tests/unit/test_version.py
cogzia-1.5.0a15.dist-info/METADATA
cogzia-1.5.0a15.dist-info/WHEEL
cogzia-1.5.0a15.dist-info/entry_points.txt
cogzia-1.5.0a15.dist-info/top_level.txt
cogzia-1.5.0a15.dist-info/RECORD
