Metadata-Version: 2.4
Name: cogzia
Version: 1.5.0a15
Summary: Cogzia Alpha v1.5 - Cloud-native AI Agent Builder
Home-page: https://app.cogzia.com
Author: Cogzia Team
Author-email: Cogzia Team <team@cogzia.com>
License: MIT
Project-URL: Homepage, https://dev.cogzia.com
Project-URL: Documentation, https://dev.cogzia.com/docs
Project-URL: Repository, https://github.com/cogzia/agent_builder
Project-URL: Issues, https://github.com/cogzia/agent_builder/issues
Project-URL: Bug Tracker, https://github.com/cogzia/agent_builder/issues
Keywords: ai,agents,mcp,cloud,automation
Classifier: Development Status :: 3 - Alpha
Classifier: Intended Audience :: Developers
Classifier: Programming Language :: Python :: 3
Classifier: Programming Language :: Python :: 3.8
Classifier: Programming Language :: Python :: 3.9
Classifier: Programming Language :: Python :: 3.10
Classifier: Programming Language :: Python :: 3.11
Classifier: Programming Language :: Python :: 3.12
Requires-Python: >=3.8
Requires-Dist: httpx>=0.25.0
Requires-Dist: aiohttp>=3.9.0
Requires-Dist: websockets>=11.0.0
Requires-Dist: rich>=13.0.0
Requires-Dist: click>=8.0.0
Requires-Dist: pydantic>=2.0.0
Requires-Dist: PyYAML>=6.0.0
Requires-Dist: pandas>=2.0.0
Requires-Dist: numpy>=1.24.0
Requires-Dist: requests>=2.28.0
Requires-Dist: python-dateutil>=2.8.0
Requires-Dist: typing-extensions>=4.0.0
Requires-Dist: jsonschema>=4.0.0
Requires-Dist: msgpack>=1.0.0
Requires-Dist: PyJWT>=2.0.0
Requires-Dist: python-dotenv>=1.0.0
Requires-Dist: google-cloud-secret-manager>=2.16.0
Requires-Dist: google-auth>=2.17.0
Requires-Dist: build>=1.2.2.post1
Requires-Dist: twine>=6.1.0
Provides-Extra: test
Requires-Dist: pytest>=7.0.0; extra == "test"
Requires-Dist: pytest-asyncio>=0.21.0; extra == "test"
Provides-Extra: dev
Dynamic: author
Dynamic: home-page
Dynamic: requires-python
